<?xml version="1.0" encoding="UTF-8"?>
<objects serializationModel="Studio.02.02.00">
	<object class="AudioFile" id="{de71b457-c352-490e-a2df-e66886f0d7a6}">
		<property name="assetPath">
			<value>Ambiences/Warehouse bossa v01 clean.mp3</value>
		</property>
		<property name="isStreaming">
			<value>true</value>
		</property>
		<property name="frequencyInKHz">
			<value>48</value>
		</property>
		<property name="channelCount">
			<value>2</value>
		</property>
		<property name="length">
			<value>91.488</value>
		</property>
		<relationship name="masterAssetFolder">
			<destination>{a1961438-bdc9-4db6-8e5e-89924b8aa068}</destination>
		</relationship>
	</object>
</objects>
